nhssynth/cli/__init__.py
nhssynth/cli/__main__.py
nhssynth/cli/common_arguments.py
nhssynth/cli/config.py
nhssynth/cli/model_arguments.py
nhssynth/cli/module_arguments.py
nhssynth/cli/module_setup.py
nhssynth/cli/run.py
nhssynth/common/__init__.py
nhssynth/common/common.py
nhssynth/common/constants.py
nhssynth/common/debugging.py
nhssynth/common/dicts.py
nhssynth/common/io.py
nhssynth/common/strings.py
nhssynth/modules/__init__.py
nhssynth/modules/dashboard/Upload.py
nhssynth/modules/dashboard/__init__.py
nhssynth/modules/dashboard/io.py
nhssynth/modules/dashboard/pages/1_Tables.py
nhssynth/modules/dashboard/pages/2_Plots.py
nhssynth/modules/dashboard/pages/3_Experiment_Configurations.py
nhssynth/modules/dashboard/pages/__init__.py
nhssynth/modules/dashboard/run.py
nhssynth/modules/dashboard/utils.py
nhssynth/modules/dataloader/__init__.py
nhssynth/modules/dataloader/constraints.py
nhssynth/modules/dataloader/io.py
nhssynth/modules/dataloader/metadata.py
nhssynth/modules/dataloader/metatransformer.py
nhssynth/modules/dataloader/missingness.py
nhssynth/modules/dataloader/run.py
nhssynth/modules/dataloader/transformers/__init__.py
nhssynth/modules/dataloader/transformers/base.py
nhssynth/modules/dataloader/transformers/categorical.py
nhssynth/modules/dataloader/transformers/continuous.py
nhssynth/modules/dataloader/transformers/datetime.py
nhssynth/modules/evaluation/__init__.py
nhssynth/modules/evaluation/aequitas.py
nhssynth/modules/evaluation/io.py
nhssynth/modules/evaluation/metrics.py
nhssynth/modules/evaluation/run.py
nhssynth/modules/evaluation/tasks.py
nhssynth/modules/evaluation/utils.py
nhssynth/modules/model/__init__.py
nhssynth/modules/model/common/__init__.py
nhssynth/modules/model/common/dp.py
nhssynth/modules/model/common/mlp.py
nhssynth/modules/model/common/model.py
nhssynth/modules/model/io.py
nhssynth/modules/model/models/__init__.py
nhssynth/modules/model/models/dpvae.py
nhssynth/modules/model/models/gan.py
nhssynth/modules/model/models/vae.py
nhssynth-0.10.2.dist-info/LICENSE
nhssynth-0.10.2.dist-info/METADATA
nhssynth-0.10.2.dist-info/WHEEL
nhssynth-0.10.2.dist-info/entry_points.txt
nhssynth-0.10.2.dist-info/RECORD
