Metadata-Version: 2.1
Name: nhssynth
Version: 0.10.2
Summary: Synthetic data generation pipeline leveraging a Differentially Private Variational Auto Encoder assessed using a variety of metrics
Home-page: https://github.com/nhsengland/NHSSynth
License: MIT
Keywords: synthetic data,privacy,fairness,machine learning
Author: HarrisonWilde
Author-email: harrisondwilde@outlook.com
Maintainer: NHSE TDAU
Maintainer-email: england.tdau@nhs.net
Requires-Python: >=3.9, !=2.7.*, !=3.0.*, !=3.1.*, !=3.2.*, !=3.3.*, !=3.4.*, !=3.5.*, !=3.6.*, !=3.7.*, !=3.8.*, !=3.12.*
Classifier: Development Status :: 3 - Alpha
Classifier: License :: OSI Approved :: MIT License
Classifier: Programming Language :: Python :: 3
Classifier: Programming Language :: Python :: 3.9
Classifier: Programming Language :: Python :: 3.10
Classifier: Programming Language :: Python :: 3.11
Requires-Dist: gower (>=0.1.2,<0.2.0)
Requires-Dist: llvmlite (>=0.40.1,<0.41.0)
Requires-Dist: networkx (>=3.1,<4.0)
Requires-Dist: opacus (>=1.4.0,<2.0.0)
Requires-Dist: pandas (>=2.0.1,<3.0.0)
Requires-Dist: plotly (>=5.16.1,<6.0.0)
Requires-Dist: pyvis (>=0.3.2,<0.4.0)
Requires-Dist: pyyaml (>=6.0,<7.0)
Requires-Dist: scikit-learn (>=1.2.2,<2.0.0)
Requires-Dist: sdmetrics (>=0.11.0,<0.12.0)
Requires-Dist: streamlit (>=1.25.0,<2.0.0)
Requires-Dist: torch (>=2.1.2,<3.0.0)
Requires-Dist: tqdm (>=4.65.0,<5.0.0)
Requires-Dist: umap-learn (>=0.5.3,<0.6.0)
Project-URL: Bug Tracker, https://github.com/nhsengland/NHSSynth/issues
Project-URL: Docs, https://nhsengland.github.io/NHSSynth
Project-URL: Repository, https://github.com/nhsengland/NHSSynth
